wakalinus/__init__.py
wakalinus/wakalinus.py
wakalinus/dic/pn_noun.json
wakalinus/dic/pn_wago.json
wakalinus-0.1.1.dist-info/LICENSE
wakalinus-0.1.1.dist-info/METADATA
wakalinus-0.1.1.dist-info/WHEEL
wakalinus-0.1.1.dist-info/top_level.txt
wakalinus-0.1.1.dist-info/RECORD
