Metadata-Version: 2.1
Name: wakalinus
Version: 0.1.1
Summary: UNKNOWN
Home-page: https://github.com/AjxLab/wakalinus
Author: Tatsuya Abe
Author-email: abe12@mccc.jp
License: MIT
Keywords: setiment nlp japanese
Platform: UNKNOWN
Classifier: License :: OSI Approved :: MIT License
Classifier: Programming Language :: Python :: 3.7
Requires-Dist: janome
